{
    "metadata": {
        "next_state_to_scrape": "ACT",
        "last_scraped_timestamp": "2025-08-08T17:34:49.093487",
        "total_stores_scraped": 17
    },
    "stores_by_state": {
        "ACT": [
            {
                "store_name": "Coles Chisholm",
                "store_id": "858"
            },
            {
                "store_name": "Coles Curtin",
                "store_id": "735"
            },
            {
                "store_name": "Coles Dickson",
                "store_id": "4814"
            },
            {
                "store_name": "Coles Gungahlin",
                "store_id": "803"
            },
            {
                "store_name": "Coles Jamison",
                "store_id": "748"
            },
            {
                "store_name": "Coles Kaleen",
                "store_id": "4785"
            },
            {
                "store_name": "Coles Manuka",
                "store_id": "859"
            },
            {
                "store_name": "Coles Tuggeranong",
                "store_id": "911"
            },
            {
                "store_name": "Coles Wanniassa",
                "store_id": "4786"
            },
            {
                "store_name": "Coles Woden",
                "store_id": "848"
            },
            {
                "store_name": "Coles Amaroo",
                "store_id": "5784"
            },
            {
                "store_name": "Coles Belconnen",
                "store_id": "779"
            },
            {
                "store_name": "Coles Canberra Civic",
                "store_id": "4787"
            }
        ],
        "NSW": [
            {
                "store_name": "Coles Armidale",
                "store_id": "8760"
            },
            {
                "store_name": "Coles Asquith",
                "store_id": "760"
            },
            {
                "store_name": "Coles Balgowlah",
                "store_id": "886"
            },
            {
                "store_name": "Coles Ballina",
                "store_id": "4401"
            },
            {
                "store_name": "Coles Bankstown",
                "store_id": "7662"
            },
            {
                "store_name": "Coles Banora Central",
                "store_id": "4577"
            },
            {
                "store_name": "Coles Bateau Bay",
                "store_id": "904"
            },
            {
                "store_name": "Coles Batemans Bay",
                "store_id": "811"
            },
            {
                "store_name": "Coles Bathurst",
                "store_id": "836"
            },
            {
                "store_name": "Coles Baulkham Hills",
                "store_id": "951"
            },
            {
                "store_name": "Coles Bega",
                "store_id": "739"
            },
            {
                "store_name": "Coles Belmont",
                "store_id": "823"
            },
            {
                "store_name": "Coles Berkeley",
                "store_id": "4387"
            },
            {
                "store_name": "Coles Berowra",
                "store_id": "929"
            },
            {
                "store_name": "Coles Blacktown",
                "store_id": "862"
            },
            {
                "store_name": "Coles Bondi Junction",
                "store_id": "809"
            },
            {
                "store_name": "Coles Bondi Westfield",
                "store_id": "853"
            },
            {
                "store_name": "Coles Bonnells Bay",
                "store_id": "5771"
            },
            {
                "store_name": "Coles Boorooma",
                "store_id": "7561"
            },
            {
                "store_name": "Coles Bowral",
                "store_id": "804"
            },
            {
                "store_name": "Coles Box Hill Carmel Village",
                "store_id": "7549"
            },
            {
                "store_name": "Coles Brighton Le Sands",
                "store_id": "831"
            },
            {
                "store_name": "Coles Broadway",
                "store_id": "839"
            },
            {
                "store_name": "Coles Broken Hill",
                "store_id": "4960"
            },
            {
                "store_name": "Coles Budgewoi",
                "store_id": "5759"
            },
            {
                "store_name": "Coles Cambridge Gardens",
                "store_id": "874"
            },
            {
                "store_name": "Coles Camden",
                "store_id": "785"
            },
            {
                "store_name": "Coles Campbelltown",
                "store_id": "906"
            },
            {
                "store_name": "Coles Casino",
                "store_id": "5694"
            },
            {
                "store_name": "Coles Castle Hill",
                "store_id": "825"
            },
            {
                "store_name": "Coles Casuarina",
                "store_id": "4460"
            },
            {
                "store_name": "Coles Casula",
                "store_id": "908"
            },
            {
                "store_name": "Coles Central Kings Cross",
                "store_id": "754"
            },
            {
                "store_name": "Coles Central Wynyard Express",
                "store_id": "840"
            },
            {
                "store_name": "Coles Cessnock",
                "store_id": "864"
            },
            {
                "store_name": "Coles Charlestown",
                "store_id": "995"
            },
            {
                "store_name": "Coles Chipping Norton",
                "store_id": "953"
            },
            {
                "store_name": "Coles Chittaway Point",
                "store_id": "5726"
            },
            {
                "store_name": "Coles Chullora",
                "store_id": "7708"
            },
            {
                "store_name": "Coles Clemton Park",
                "store_id": "4812"
            },
            {
                "store_name": "Coles Coffs Harbour",
                "store_id": "5679"
            },
            {
                "store_name": "Coles Cooma",
                "store_id": "703"
            },
            {
                "store_name": "Coles Corrimal",
                "store_id": "890"
            },
            {
                "store_name": "Coles Cowra",
                "store_id": "5749"
            },
            {
                "store_name": "Coles Cs Stctk Serv NSW M1",
                "store_id": "5813"
            },
            {
                "store_name": "Coles Cs Stctk Serv NSW M2",
                "store_id": "5814"
            },
            {
                "store_name": "Coles Cs Stctk Serv NSW M3",
                "store_id": "5815"
            },
            {
                "store_name": "Coles Dapto",
                "store_id": "778"
            },
            {
                "store_name": "Coles Dee Why",
                "store_id": "784"
            },
            {
                "store_name": "Coles Deniliquin",
                "store_id": "675"
            },
            {
                "store_name": "Coles Doonside",
                "store_id": "827"
            },
            {
                "store_name": "Coles Dubbo",
                "store_id": "788"
            },
            {
                "store_name": "Coles East Village",
                "store_id": "7569"
            },
            {
                "store_name": "Coles Eastgardens",
                "store_id": "909"
            },
            {
                "store_name": "Coles Eden",
                "store_id": "5697"
            },
            {
                "store_name": "Coles Edensor Park",
                "store_id": "936"
            },
            {
                "store_name": "Coles Edgecliff",
                "store_id": "899"
            },
            {
                "store_name": "Coles Edgeworth",
                "store_id": "879"
            },
            {
                "store_name": "Coles Edmondson Park",
                "store_id": "7823"
            },
            {
                "store_name": "Coles Elara Marsden Park",
                "store_id": "7710"
            },
            {
                "store_name": "Coles Engadine",
                "store_id": "793"
            },
            {
                "store_name": "Coles Erina",
                "store_id": "885"
            },
            {
                "store_name": "Coles Fairy Meadow",
                "store_id": "927"
            },
            {
                "store_name": "Coles Figtree",
                "store_id": "716"
            },
            {
                "store_name": "Coles Fletcher",
                "store_id": "940"
            },
            {
                "store_name": "Coles Forster",
                "store_id": "901"
            },
            {
                "store_name": "Coles Glen Innes",
                "store_id": "5597"
            },
            {
                "store_name": "Coles Glendale",
                "store_id": "893"
            },
            {
                "store_name": "Coles Glenfield Park",
                "store_id": "725"
            },
            {
                "store_name": "Coles Glenmore Park",
                "store_id": "5590"
            },
            {
                "store_name": "Coles Goonellabah",
                "store_id": "4535"
            },
            {
                "store_name": "Coles Goulburn",
                "store_id": "802"
            },
            {
                "store_name": "Coles Grafton",
                "store_id": "4485"
            },
            {
                "store_name": "Coles Green Hills",
                "store_id": "898"
            },
            {
                "store_name": "Coles Green Point",
                "store_id": "5689"
            },
            {
                "store_name": "Coles Green Valley",
                "store_id": "834"
            },
            {
                "store_name": "Coles Greenacre",
                "store_id": "5792"
            },
            {
                "store_name": "Coles Griffith",
                "store_id": "838"
            },
            {
                "store_name": "Coles Gunnedah",
                "store_id": "4522"
            },
            {
                "store_name": "Coles Harrington Park",
                "store_id": "713"
            },
            {
                "store_name": "Coles Helensburgh",
                "store_id": "5736"
            },
            {
                "store_name": "Coles Hornsby",
                "store_id": "860"
            },
            {
                "store_name": "Coles Huntlee",
                "store_id": "7702"
            },
            {
                "store_name": "Coles Hurstville",
                "store_id": "782"
            },
            {
                "store_name": "Coles Hurstville Station",
                "store_id": "942"
            },
            {
                "store_name": "Coles Illawong",
                "store_id": "847"
            },
            {
                "store_name": "Coles Ingleburn",
                "store_id": "4177"
            },
            {
                "store_name": "Coles Inverell",
                "store_id": "4444"
            },
            {
                "store_name": "Coles Jewellstown",
                "store_id": "4178"
            },
            {
                "store_name": "Coles Kareela",
                "store_id": "783"
            },
            {
                "store_name": "Coles Katoomba",
                "store_id": "921"
            },
            {
                "store_name": "Coles Kellyville",
                "store_id": "883"
            },
            {
                "store_name": "Coles Kempsey",
                "store_id": "5680"
            },
            {
                "store_name": "Coles Killarney Vale",
                "store_id": "5696"
            },
            {
                "store_name": "Coles Kincumber",
                "store_id": "5730"
            },
            {
                "store_name": "Coles Kings Langley",
                "store_id": "796"
            },
            {
                "store_name": "Coles Kirrawee",
                "store_id": "5588"
            },
            {
                "store_name": "Coles Kotara",
                "store_id": "833"
            },
            {
                "store_name": "Coles Kurri Kurri",
                "store_id": "999"
            },
            {
                "store_name": "Coles Lake Haven",
                "store_id": "819"
            },
            {
                "store_name": "Coles Lake Innes Village",
                "store_id": "5684"
            },
            {
                "store_name": "Coles Lake Macquarie",
                "store_id": "5807"
            },
            {
                "store_name": "Coles Laurieton",
                "store_id": "5685"
            },
            {
                "store_name": "Coles Lavington",
                "store_id": "617"
            },
            {
                "store_name": "Coles Lighthouse Beach",
                "store_id": "5683"
            },
            {
                "store_name": "Coles Lisarow",
                "store_id": "7554"
            },
            {
                "store_name": "Coles Lismore",
                "store_id": "4477"
            },
            {
                "store_name": "Coles Lithgow",
                "store_id": "801"
            },
            {
                "store_name": "Coles Liverpool Westfield",
                "store_id": "723"
            },
            {
                "store_name": "Coles Local Earlwood",
                "store_id": "750"
            },
            {
                "store_name": "Coles Local Manly Corso",
                "store_id": "815"
            },
            {
                "store_name": "Coles Local Newport",
                "store_id": "814"
            },
            {
                "store_name": "Coles Local Pagewood",
                "store_id": "5751"
            },
            {
                "store_name": "Coles Local Rose Bay",
                "store_id": "770"
            },
            {
                "store_name": "Coles Local Sydney Cbd - York Street",
                "store_id": "7689"
            },
            {
                "store_name": "Coles Macarthur Square",
                "store_id": "4813"
            },
            {
                "store_name": "Coles Manly Peninsula",
                "store_id": "869"
            },
            {
                "store_name": "Coles Manly Vale",
                "store_id": "745"
            },
            {
                "store_name": "Coles Marketown",
                "store_id": "993"
            },
            {
                "store_name": "Coles Maroubra Junction",
                "store_id": "737"
            },
            {
                "store_name": "Coles Marrickville",
                "store_id": "4166"
            },
            {
                "store_name": "Coles Mayfield",
                "store_id": "5798"
            },
            {
                "store_name": "Coles Medowie",
                "store_id": "7555"
            },
            {
                "store_name": "Coles Miranda",
                "store_id": "766"
            },
            {
                "store_name": "Coles Miranda",
                "store_id": "790"
            },
            {
                "store_name": "Coles Mona Vale",
                "store_id": "884"
            },
            {
                "store_name": "Coles Moonee Beach",
                "store_id": "5681"
            },
            {
                "store_name": "Coles Moree",
                "store_id": "4473"
            },
            {
                "store_name": "Coles Morisset",
                "store_id": "950"
            },
            {
                "store_name": "Coles Moss Vale",
                "store_id": "5691"
            },
            {
                "store_name": "Coles Mount Druitt",
                "store_id": "726"
            },
            {
                "store_name": "Coles Mt Annan",
                "store_id": "5769"
            },
            {
                "store_name": "Coles Mudgee",
                "store_id": "5753"
            },
            {
                "store_name": "Coles Murwillumbah",
                "store_id": "4505"
            },
            {
                "store_name": "Coles Narellan",
                "store_id": "5800"
            },
            {
                "store_name": "Coles Narrabri",
                "store_id": "8769"
            },
            {
                "store_name": "Coles Narrandera",
                "store_id": "7579"
            },
            {
                "store_name": "Coles Narromine",
                "store_id": "5755"
            },
            {
                "store_name": "Coles Neutral Bay Grosvenor St",
                "store_id": "4974"
            },
            {
                "store_name": "Coles Newcastle",
                "store_id": "813"
            },
            {
                "store_name": "Coles North Richmond",
                "store_id": "5777"
            },
            {
                "store_name": "Coles Norwest",
                "store_id": "851"
            },
            {
                "store_name": "Coles Nowra",
                "store_id": "780"
            },
            {
                "store_name": "Coles Oatley West",
                "store_id": "923"
            },
            {
                "store_name": "Coles Ocean Shores",
                "store_id": "4651"
            },
            {
                "store_name": "Coles Old Bar",
                "store_id": "5598"
            },
            {
                "store_name": "Coles Online Hub Store Ocado - Sydney",
                "store_id": "7673"
            },
            {
                "store_name": "Coles Online Hub Store Ocado - Sydney - Team Shop",
                "store_id": "7594"
            },
            {
                "store_name": "Coles Online Hub Store Ocado Spoke - Alexandria",
                "store_id": "5827"
            },
            {
                "store_name": "Coles Oran Park",
                "store_id": "5558"
            },
            {
                "store_name": "Coles Orange",
                "store_id": "835"
            },
            {
                "store_name": "Coles Parkes",
                "store_id": "5757"
            },
            {
                "store_name": "Coles Penrith",
                "store_id": "903"
            },
            {
                "store_name": "Coles Penrith Westfield",
                "store_id": "7556"
            },
            {
                "store_name": "Coles Picton",
                "store_id": "711"
            },
            {
                "store_name": "Coles Port Macquarie",
                "store_id": "5686"
            },
            {
                "store_name": "Coles Pyrmont",
                "store_id": "728"
            },
            {
                "store_name": "Coles Queanbeyan",
                "store_id": "820"
            },
            {
                "store_name": "Coles Ramsgate",
                "store_id": "762"
            },
            {
                "store_name": "Coles Randwick",
                "store_id": "800"
            },
            {
                "store_name": "Coles Revesby",
                "store_id": "7558"
            },
            {
                "store_name": "Coles Richmond",
                "store_id": "792"
            },
            {
                "store_name": "Coles Ropes Crossing",
                "store_id": "970"
            },
            {
                "store_name": "Coles Roselands",
                "store_id": "720"
            },
            {
                "store_name": "Coles Rouse Hill",
                "store_id": "924"
            },
            {
                "store_name": "Coles Rutherford",
                "store_id": "946"
            },
            {
                "store_name": "Coles Salamander Bay",
                "store_id": "7565"
            },
            {
                "store_name": "Coles San Remo",
                "store_id": "882"
            },
            {
                "store_name": "Coles Schofields",
                "store_id": "7572"
            },
            {
                "store_name": "Coles Scone",
                "store_id": "939"
            },
            {
                "store_name": "Coles Shellharbour",
                "store_id": "5797"
            },
            {
                "store_name": "Coles Singleton",
                "store_id": "945"
            },
            {
                "store_name": "Coles South Grafton",
                "store_id": "5693"
            },
            {
                "store_name": "Coles South Tamworth",
                "store_id": "5796"
            },
            {
                "store_name": "Coles South West Rocks",
                "store_id": "5678"
            },
            {
                "store_name": "Coles St Ives",
                "store_id": "5676"
            },
            {
                "store_name": "Coles Stanhope Gardens",
                "store_id": "702"
            },
            {
                "store_name": "Coles Sth Muswellbrook",
                "store_id": "5776"
            },
            {
                "store_name": "Coles Surry Hills",
                "store_id": "7671"
            },
            {
                "store_name": "Coles Sutherland",
                "store_id": "4789"
            },
            {
                "store_name": "Coles Swansea",
                "store_id": "807"
            },
            {
                "store_name": "Coles Sylvania",
                "store_id": "772"
            },
            {
                "store_name": "Coles Tamworth",
                "store_id": "8761"
            },
            {
                "store_name": "Coles Tamworth North",
                "store_id": "8770"
            },
            {
                "store_name": "Coles Tanilba Bay",
                "store_id": "989"
            },
            {
                "store_name": "Coles Taree Manning Mall",
                "store_id": "967"
            },
            {
                "store_name": "Coles Tea Gardens",
                "store_id": "5692"
            },
            {
                "store_name": "Coles Tenterfield",
                "store_id": "5695"
            },
            {
                "store_name": "Coles The Entrance",
                "store_id": "798"
            },
            {
                "store_name": "Coles The Grand (dee Why)",
                "store_id": "944"
            },
            {
                "store_name": "Coles Thirroul",
                "store_id": "5698"
            },
            {
                "store_name": "Coles Thornton",
                "store_id": "5690"
            },
            {
                "store_name": "Coles Thurgoona Village",
                "store_id": "5828"
            },
            {
                "store_name": "Coles Toormina",
                "store_id": "5682"
            },
            {
                "store_name": "Coles Toronto",
                "store_id": "850"
            },
            {
                "store_name": "Coles Toukley",
                "store_id": "781"
            },
            {
                "store_name": "Coles Tuggerah",
                "store_id": "752"
            },
            {
                "store_name": "Coles Tumut",
                "store_id": "757"
            },
            {
                "store_name": "Coles Turramurra",
                "store_id": "717"
            },
            {
                "store_name": "Coles Tweed City",
                "store_id": "4459"
            },
            {
                "store_name": "Coles Tweed Heads",
                "store_id": "4474"
            },
            {
                "store_name": "Coles Ulladulla",
                "store_id": "845"
            },
            {
                "store_name": "Coles Umina Beach",
                "store_id": "5733"
            },
            {
                "store_name": "Coles Vincentia",
                "store_id": "7591"
            },
            {
                "store_name": "Coles Wadalba",
                "store_id": "992"
            },
            {
                "store_name": "Coles Wagga Wagga",
                "store_id": "704"
            },
            {
                "store_name": "Coles Wallsend",
                "store_id": "824"
            },
            {
                "store_name": "Coles Waratah",
                "store_id": "746"
            },
            {
                "store_name": "Coles Warners Bay",
                "store_id": "880"
            },
            {
                "store_name": "Coles Warrawong",
                "store_id": "822"
            },
            {
                "store_name": "Coles Warriewood",
                "store_id": "797"
            },
            {
                "store_name": "Coles Warringah",
                "store_id": "897"
            },
            {
                "store_name": "Coles Waterloo",
                "store_id": "987"
            },
            {
                "store_name": "Coles Wattle Grove",
                "store_id": "842"
            },
            {
                "store_name": "Coles Wellington",
                "store_id": "5714"
            },
            {
                "store_name": "Coles West Gosford",
                "store_id": "821"
            },
            {
                "store_name": "Coles West Pennant Hills",
                "store_id": "761"
            },
            {
                "store_name": "Coles Wetherill Park",
                "store_id": "7596"
            },
            {
                "store_name": "Coles Willowdale",
                "store_id": "5806"
            },
            {
                "store_name": "Coles Windsor",
                "store_id": "844"
            },
            {
                "store_name": "Coles Wingham",
                "store_id": "5778"
            },
            {
                "store_name": "Coles Winmalee",
                "store_id": "709"
            },
            {
                "store_name": "Coles Wollongong",
                "store_id": "7587"
            },
            {
                "store_name": "Coles World Square",
                "store_id": "710"
            },
            {
                "store_name": "Coles Woy Woy",
                "store_id": "905"
            },
            {
                "store_name": "Coles Wyoming",
                "store_id": "786"
            },
            {
                "store_name": "Coles Wyong",
                "store_id": "925"
            },
            {
                "store_name": "Coles Yamba",
                "store_id": "4551"
            },
            {
                "store_name": "Coles Albury",
                "store_id": "693"
            },
            {
                "store_name": "Coles Alstonville",
                "store_id": "8750"
            }
        ],
        "NT": [
            {
                "store_name": "Coles Casuarina",
                "store_id": "404"
            },
            {
                "store_name": "Coles Coolalinga",
                "store_id": "486"
            },
            {
                "store_name": "Coles Darwin",
                "store_id": "460"
            },
            {
                "store_name": "Coles Northlakes",
                "store_id": "472"
            },
            {
                "store_name": "Coles Oasis (palmerston)",
                "store_id": "219"
            },
            {
                "store_name": "Coles Palmerston",
                "store_id": "450"
            },
            {
                "store_name": "Coles Alice Springs",
                "store_id": "418"
            },
            {
                "store_name": "Coles Bradshaw St",
                "store_id": "4947"
            }
        ],
        "QLD": [
            {
                "store_name": "Coles Andergrove",
                "store_id": "4389"
            },
            {
                "store_name": "Coles Annandale",
                "store_id": "4563"
            },
            {
                "store_name": "Coles Arana Hills",
                "store_id": "4492"
            },
            {
                "store_name": "Coles Arundel",
                "store_id": "4555"
            },
            {
                "store_name": "Coles Ashgrove",
                "store_id": "4471"
            },
            {
                "store_name": "Coles Australia Fair",
                "store_id": "4500"
            },
            {
                "store_name": "Coles Ayr",
                "store_id": "4510"
            },
            {
                "store_name": "Coles Bay Central",
                "store_id": "4529"
            },
            {
                "store_name": "Coles Beaudesert",
                "store_id": "4511"
            },
            {
                "store_name": "Coles Beenleigh",
                "store_id": "4449"
            },
            {
                "store_name": "Coles Benowa",
                "store_id": "8739"
            },
            {
                "store_name": "Coles Benowa Village",
                "store_id": "4390"
            },
            {
                "store_name": "Coles Birtinya",
                "store_id": "7836"
            },
            {
                "store_name": "Coles Bracken Ridge",
                "store_id": "4524"
            },
            {
                "store_name": "Coles Bray Park",
                "store_id": "4480"
            },
            {
                "store_name": "Coles Brookside",
                "store_id": "4430"
            },
            {
                "store_name": "Coles Browns Plains",
                "store_id": "4525"
            },
            {
                "store_name": "Coles Buderim",
                "store_id": "7835"
            },
            {
                "store_name": "Coles Bundaberg",
                "store_id": "4497"
            },
            {
                "store_name": "Coles Burleigh Waters",
                "store_id": "4520"
            },
            {
                "store_name": "Coles Burpengary",
                "store_id": "4582"
            },
            {
                "store_name": "Coles Bushland Beach",
                "store_id": "5803"
            },
            {
                "store_name": "Coles Caboolture",
                "store_id": "4404"
            },
            {
                "store_name": "Coles Caboolture North  - Big Fish",
                "store_id": "4091"
            },
            {
                "store_name": "Coles Cairns Central",
                "store_id": "4536"
            },
            {
                "store_name": "Coles Cairns Smithfield",
                "store_id": "4532"
            },
            {
                "store_name": "Coles Caloundra",
                "store_id": "4478"
            },
            {
                "store_name": "Coles Cannon Hill",
                "store_id": "4464"
            },
            {
                "store_name": "Coles Cannonvale",
                "store_id": "4598"
            },
            {
                "store_name": "Coles Capalaba",
                "store_id": "4509"
            },
            {
                "store_name": "Coles Carindale (westfield)",
                "store_id": "4574"
            },
            {
                "store_name": "Coles Castletown",
                "store_id": "4689"
            },
            {
                "store_name": "Coles Central Brisbane Myer Express",
                "store_id": "4564"
            },
            {
                "store_name": "Coles Cleveland",
                "store_id": "4540"
            },
            {
                "store_name": "Coles Clifford Gardens",
                "store_id": "4645"
            },
            {
                "store_name": "Coles Clifton Beach",
                "store_id": "4581"
            },
            {
                "store_name": "Coles Coolum",
                "store_id": "4420"
            },
            {
                "store_name": "Coles Coomera City Centre",
                "store_id": "4669"
            },
            {
                "store_name": "Coles Coomera Westfield",
                "store_id": "4383"
            },
            {
                "store_name": "Coles Corinda",
                "store_id": "4495"
            },
            {
                "store_name": "Coles Dalby",
                "store_id": "4490"
            },
            {
                "store_name": "Coles Deception Bay",
                "store_id": "7559"
            },
            {
                "store_name": "Coles Deeragun",
                "store_id": "4569"
            },
            {
                "store_name": "Coles Earlville",
                "store_id": "4409"
            },
            {
                "store_name": "Coles Edmonton",
                "store_id": "4410"
            },
            {
                "store_name": "Coles Emerald",
                "store_id": "4541"
            },
            {
                "store_name": "Coles Fairfield Central - Townsville",
                "store_id": "7824"
            },
            {
                "store_name": "Coles Fairfield Gardens - Brisbane",
                "store_id": "4512"
            },
            {
                "store_name": "Coles Ferny Grove",
                "store_id": "8712"
            },
            {
                "store_name": "Coles Flagstone",
                "store_id": "4090"
            },
            {
                "store_name": "Coles Forest Lake",
                "store_id": "4421"
            },
            {
                "store_name": "Coles Gatton",
                "store_id": "4483"
            },
            {
                "store_name": "Coles Gladstone",
                "store_id": "4406"
            },
            {
                "store_name": "Coles Glenvale",
                "store_id": "4417"
            },
            {
                "store_name": "Coles Goondiwindi",
                "store_id": "4384"
            },
            {
                "store_name": "Coles Greenslopes",
                "store_id": "4507"
            },
            {
                "store_name": "Coles Gympie",
                "store_id": "4440"
            },
            {
                "store_name": "Coles Helensvale",
                "store_id": "4584"
            },
            {
                "store_name": "Coles Helensvale Plaza",
                "store_id": "8732"
            },
            {
                "store_name": "Coles Hervey Bay",
                "store_id": "4513"
            },
            {
                "store_name": "Coles Highfields",
                "store_id": "4452"
            },
            {
                "store_name": "Coles Hope Island",
                "store_id": "4418"
            },
            {
                "store_name": "Coles Indooroopilly",
                "store_id": "4660"
            },
            {
                "store_name": "Coles Ingham",
                "store_id": "4442"
            },
            {
                "store_name": "Coles Innisfail",
                "store_id": "4441"
            },
            {
                "store_name": "Coles Ipswich",
                "store_id": "4566"
            },
            {
                "store_name": "Coles Ipswich Riverlink",
                "store_id": "4596"
            },
            {
                "store_name": "Coles Jimboomba",
                "store_id": "4453"
            },
            {
                "store_name": "Coles Jindalee",
                "store_id": "8714"
            },
            {
                "store_name": "Coles Kallangur",
                "store_id": "8715"
            },
            {
                "store_name": "Coles Karalee",
                "store_id": "4565"
            },
            {
                "store_name": "Coles Kawana Waters",
                "store_id": "4435"
            },
            {
                "store_name": "Coles Kenmore",
                "store_id": "4515"
            },
            {
                "store_name": "Coles Kensington",
                "store_id": "4810"
            },
            {
                "store_name": "Coles Kippa Ring",
                "store_id": "4519"
            },
            {
                "store_name": "Coles Labrador",
                "store_id": "4446"
            },
            {
                "store_name": "Coles Local Brisbane - Adelaide St",
                "store_id": "4334"
            },
            {
                "store_name": "Coles Local Coorparoo",
                "store_id": "4467"
            },
            {
                "store_name": "Coles Local Taringa",
                "store_id": "4694"
            },
            {
                "store_name": "Coles Local Woolloongabba",
                "store_id": "4571"
            },
            {
                "store_name": "Coles Loganholme",
                "store_id": "4407"
            },
            {
                "store_name": "Coles Mackay (caneland)",
                "store_id": "4558"
            },
            {
                "store_name": "Coles Mackay (parkside)",
                "store_id": "4425"
            },
            {
                "store_name": "Coles Mango Hill",
                "store_id": "4436"
            },
            {
                "store_name": "Coles Mareeba",
                "store_id": "4482"
            },
            {
                "store_name": "Coles Maroochydore",
                "store_id": "4523"
            },
            {
                "store_name": "Coles Marsden",
                "store_id": "4502"
            },
            {
                "store_name": "Coles Maryborough",
                "store_id": "4659"
            },
            {
                "store_name": "Coles Mermaid Waters",
                "store_id": "8741"
            },
            {
                "store_name": "Coles Miami",
                "store_id": "4583"
            },
            {
                "store_name": "Coles Middle Park",
                "store_id": "4557"
            },
            {
                "store_name": "Coles Milton Village",
                "store_id": "7588"
            },
            {
                "store_name": "Coles Moggill",
                "store_id": "4652"
            },
            {
                "store_name": "Coles Mooloolaba",
                "store_id": "4550"
            },
            {
                "store_name": "Coles Moranbah",
                "store_id": "4503"
            },
            {
                "store_name": "Coles Morayfield",
                "store_id": "8721"
            },
            {
                "store_name": "Coles Morningside",
                "store_id": "4578"
            },
            {
                "store_name": "Coles Mount Gravatt",
                "store_id": "4570"
            },
            {
                "store_name": "Coles Mount Gravatt Plaza",
                "store_id": "4392"
            },
            {
                "store_name": "Coles Mount Isa",
                "store_id": "4487"
            },
            {
                "store_name": "Coles Mount Ommaney",
                "store_id": "4412"
            },
            {
                "store_name": "Coles Mount Pleasant",
                "store_id": "4481"
            },
            {
                "store_name": "Coles Mount Sheridan",
                "store_id": "4567"
            },
            {
                "store_name": "Coles Mount Warren Park",
                "store_id": "4388"
            },
            {
                "store_name": "Coles Mudgeeraba",
                "store_id": "4597"
            },
            {
                "store_name": "Coles Murrumba Downs",
                "store_id": "4561"
            },
            {
                "store_name": "Coles Nambour",
                "store_id": "4438"
            },
            {
                "store_name": "Coles Nerang",
                "store_id": "4501"
            },
            {
                "store_name": "Coles Nerang Fair",
                "store_id": "4560"
            },
            {
                "store_name": "Coles New Farm",
                "store_id": "4537"
            },
            {
                "store_name": "Coles Newmarket",
                "store_id": "4528"
            },
            {
                "store_name": "Coles Noosa",
                "store_id": "4447"
            },
            {
                "store_name": "Coles North Lakes",
                "store_id": "4545"
            },
            {
                "store_name": "Coles North Shore",
                "store_id": "4674"
            },
            {
                "store_name": "Coles North Ward",
                "store_id": "4649"
            },
            {
                "store_name": "Coles Northern Beaches",
                "store_id": "4419"
            },
            {
                "store_name": "Coles Ormeau",
                "store_id": "8736"
            },
            {
                "store_name": "Coles Ormeau Village",
                "store_id": "4437"
            },
            {
                "store_name": "Coles Pacific Fair",
                "store_id": "4368"
            },
            {
                "store_name": "Coles Pacific Pines",
                "store_id": "4663"
            },
            {
                "store_name": "Coles Pallara",
                "store_id": "5559"
            },
            {
                "store_name": "Coles Palm Beach",
                "store_id": "7834"
            },
            {
                "store_name": "Coles Park Ridge",
                "store_id": "4424"
            },
            {
                "store_name": "Coles Pelican Waters",
                "store_id": "4559"
            },
            {
                "store_name": "Coles Peregian Springs",
                "store_id": "8758"
            },
            {
                "store_name": "Coles Petrie Terrace",
                "store_id": "4461"
            },
            {
                "store_name": "Coles Pimpama City Shopping Centre",
                "store_id": "4835"
            },
            {
                "store_name": "Coles Port Douglas",
                "store_id": "4546"
            },
            {
                "store_name": "Coles Redbank",
                "store_id": "4504"
            },
            {
                "store_name": "Coles Redbank Plains",
                "store_id": "4783"
            },
            {
                "store_name": "Coles Redcliffe",
                "store_id": "4422"
            },
            {
                "store_name": "Coles Redlynch",
                "store_id": "4381"
            },
            {
                "store_name": "Coles Ripley Town Centre",
                "store_id": "4667"
            },
            {
                "store_name": "Coles Robina",
                "store_id": "4427"
            },
            {
                "store_name": "Coles Rochedale",
                "store_id": "4386"
            },
            {
                "store_name": "Coles Rockhampton North",
                "store_id": "4455"
            },
            {
                "store_name": "Coles Rockhampton South",
                "store_id": "4518"
            },
            {
                "store_name": "Coles Runaway Bay",
                "store_id": "4530"
            },
            {
                "store_name": "Coles Silkstone Village",
                "store_id": "4782"
            },
            {
                "store_name": "Coles Sippy Downs",
                "store_id": "4647"
            },
            {
                "store_name": "Coles Southport Park",
                "store_id": "4653"
            },
            {
                "store_name": "Coles Springfield",
                "store_id": "4533"
            },
            {
                "store_name": "Coles Springfield Orion",
                "store_id": "4666"
            },
            {
                "store_name": "Coles Springwood",
                "store_id": "4472"
            },
            {
                "store_name": "Coles Stocktake Service QLDM1",
                "store_id": "5816"
            },
            {
                "store_name": "Coles Stocktake Service QLDM2",
                "store_id": "5817"
            },
            {
                "store_name": "Coles Strathpine",
                "store_id": "4411"
            },
            {
                "store_name": "Coles Sunnybank Hills",
                "store_id": "4671"
            },
            {
                "store_name": "Coles Surfers Paradise",
                "store_id": "4554"
            },
            {
                "store_name": "Coles Sydney Street",
                "store_id": "4587"
            },
            {
                "store_name": "Coles Tannum Sands",
                "store_id": "4580"
            },
            {
                "store_name": "Coles The Gap",
                "store_id": "4506"
            },
            {
                "store_name": "Coles The Pines",
                "store_id": "4405"
            },
            {
                "store_name": "Coles The Willows",
                "store_id": "4527"
            },
            {
                "store_name": "Coles Thornlands",
                "store_id": "7681"
            },
            {
                "store_name": "Coles Thuringowa",
                "store_id": "4655"
            },
            {
                "store_name": "Coles Toowong",
                "store_id": "4508"
            },
            {
                "store_name": "Coles Toowoomba Grand Central",
                "store_id": "4534"
            },
            {
                "store_name": "Coles Toowoomba North",
                "store_id": "4658"
            },
            {
                "store_name": "Coles Toowoomba South",
                "store_id": "4491"
            },
            {
                "store_name": "Coles Upper Coomera",
                "store_id": "4576"
            },
            {
                "store_name": "Coles Upper Coomera Village",
                "store_id": "8737"
            },
            {
                "store_name": "Coles Upper Mount Gravatt",
                "store_id": "4595"
            },
            {
                "store_name": "Coles Varsity",
                "store_id": "7687"
            },
            {
                "store_name": "Coles Victoria Point",
                "store_id": "8729"
            },
            {
                "store_name": "Coles Warwick",
                "store_id": "4662"
            },
            {
                "store_name": "Coles Waterford",
                "store_id": "8757"
            },
            {
                "store_name": "Coles West End",
                "store_id": "4553"
            },
            {
                "store_name": "Coles Westcourt",
                "store_id": "4443"
            },
            {
                "store_name": "Coles Wilsonton",
                "store_id": "4433"
            },
            {
                "store_name": "Coles Worongary",
                "store_id": "4572"
            },
            {
                "store_name": "Coles Wynnum",
                "store_id": "4451"
            },
            {
                "store_name": "Coles Wynnum West",
                "store_id": "4539"
            },
            {
                "store_name": "Coles Yamanto",
                "store_id": "4089"
            },
            {
                "store_name": "Coles Yarrabilba",
                "store_id": "4784"
            },
            {
                "store_name": "Coles Yeppoon",
                "store_id": "8731"
            },
            {
                "store_name": "Coles Aitkenvale",
                "store_id": "4494"
            },
            {
                "store_name": "Coles Albany Creek",
                "store_id": "4516"
            }
        ],
        "SA": [
            {
                "store_name": "Coles Berri",
                "store_id": "451"
            },
            {
                "store_name": "Coles Blackwood",
                "store_id": "447"
            },
            {
                "store_name": "Coles Bridgewater",
                "store_id": "445"
            },
            {
                "store_name": "Coles Burnside",
                "store_id": "453"
            },
            {
                "store_name": "Coles Christies Beach",
                "store_id": "4933"
            },
            {
                "store_name": "Coles Churchill",
                "store_id": "7609"
            },
            {
                "store_name": "Coles Churchill",
                "store_id": "4972"
            },
            {
                "store_name": "Coles Craigmore",
                "store_id": "4921"
            },
            {
                "store_name": "Coles Dernancourt",
                "store_id": "408"
            },
            {
                "store_name": "Coles Edwardstown",
                "store_id": "452"
            },
            {
                "store_name": "Coles Elizabeth",
                "store_id": "462"
            },
            {
                "store_name": "Coles Findon",
                "store_id": "403"
            },
            {
                "store_name": "Coles Firle",
                "store_id": "401"
            },
            {
                "store_name": "Coles Gawler",
                "store_id": "444"
            },
            {
                "store_name": "Coles Gawler Green",
                "store_id": "4978"
            },
            {
                "store_name": "Coles Glenelg",
                "store_id": "420"
            },
            {
                "store_name": "Coles Greenacres",
                "store_id": "4948"
            },
            {
                "store_name": "Coles Ingle Farm",
                "store_id": "423"
            },
            {
                "store_name": "Coles Ingle Farm Walkleys Rd",
                "store_id": "4949"
            },
            {
                "store_name": "Coles Kurralta Park",
                "store_id": "406"
            },
            {
                "store_name": "Coles Marion",
                "store_id": "458"
            },
            {
                "store_name": "Coles Mclaren Vale",
                "store_id": "4961"
            },
            {
                "store_name": "Coles Mount Barker",
                "store_id": "4940"
            },
            {
                "store_name": "Coles Mount Gambier",
                "store_id": "7707"
            },
            {
                "store_name": "Coles Munno Para",
                "store_id": "4924"
            },
            {
                "store_name": "Coles Murray Bridge",
                "store_id": "4970"
            },
            {
                "store_name": "Coles Newton",
                "store_id": "446"
            },
            {
                "store_name": "Coles Noarlunga",
                "store_id": "437"
            },
            {
                "store_name": "Coles Northpark",
                "store_id": "471"
            },
            {
                "store_name": "Coles Norwood",
                "store_id": "7720"
            },
            {
                "store_name": "Coles Parabanks",
                "store_id": "4981"
            },
            {
                "store_name": "Coles Paralowie",
                "store_id": "4929"
            },
            {
                "store_name": "Coles Park Holme",
                "store_id": "419"
            },
            {
                "store_name": "Coles Port Augusta",
                "store_id": "456"
            },
            {
                "store_name": "Coles Port Lincoln",
                "store_id": "440"
            },
            {
                "store_name": "Coles Port Pirie",
                "store_id": "442"
            },
            {
                "store_name": "Coles Prospect",
                "store_id": "461"
            },
            {
                "store_name": "Coles Reynella",
                "store_id": "436"
            },
            {
                "store_name": "Coles Rundle Place",
                "store_id": "4964"
            },
            {
                "store_name": "Coles Salisbury Downs",
                "store_id": "439"
            },
            {
                "store_name": "Coles St Agnes",
                "store_id": "414"
            },
            {
                "store_name": "Coles St Clair",
                "store_id": "4971"
            },
            {
                "store_name": "Coles Stocktake Service SA",
                "store_id": "5808"
            },
            {
                "store_name": "Coles Tea Tree Plaza",
                "store_id": "459"
            },
            {
                "store_name": "Coles Test-Store Name",
                "store_id": "1111"
            },
            {
                "store_name": "Coles The Avenues",
                "store_id": "448"
            },
            {
                "store_name": "Coles Unley",
                "store_id": "430"
            },
            {
                "store_name": "Coles Victor Harbor",
                "store_id": "7832"
            },
            {
                "store_name": "Coles Warradale",
                "store_id": "4982"
            },
            {
                "store_name": "Coles Welland",
                "store_id": "429"
            },
            {
                "store_name": "Coles West Lakes",
                "store_id": "455"
            },
            {
                "store_name": "Coles Whyalla",
                "store_id": "4966"
            },
            {
                "store_name": "Coles Aberfoyle Park",
                "store_id": "4942"
            },
            {
                "store_name": "Coles Anzac Highway",
                "store_id": "4945"
            }
        ],
        "TAS": [
            {
                "store_name": "Coles Charles Street",
                "store_id": "7656"
            },
            {
                "store_name": "Coles Devonport",
                "store_id": "7621"
            },
            {
                "store_name": "Coles Eastlands",
                "store_id": "7602"
            },
            {
                "store_name": "Coles Glebe Hill",
                "store_id": "7547"
            },
            {
                "store_name": "Coles Glenorchy",
                "store_id": "7645"
            },
            {
                "store_name": "Coles Kingston",
                "store_id": "7629"
            },
            {
                "store_name": "Coles Meadow Mews",
                "store_id": "7646"
            },
            {
                "store_name": "Coles Mowbray",
                "store_id": "7502"
            },
            {
                "store_name": "Coles New Town",
                "store_id": "7523"
            },
            {
                "store_name": "Coles Newstead",
                "store_id": "7659"
            },
            {
                "store_name": "Coles Racecourse",
                "store_id": "7562"
            },
            {
                "store_name": "Coles Sandy Bay",
                "store_id": "7505"
            },
            {
                "store_name": "Coles Sorell",
                "store_id": "7500"
            },
            {
                "store_name": "Coles Ulverstone",
                "store_id": "7606"
            },
            {
                "store_name": "Coles Wellington St",
                "store_id": "7658"
            },
            {
                "store_name": "Coles Bridgewater",
                "store_id": "7647"
            },
            {
                "store_name": "Coles Burnie",
                "store_id": "7541"
            }
        ],
        "VIC": [
            {
                "store_name": "Coles Aurora Village",
                "store_id": "7771"
            },
            {
                "store_name": "Coles Bacchus Marsh",
                "store_id": "672"
            },
            {
                "store_name": "Coles Bairnsdale",
                "store_id": "548"
            },
            {
                "store_name": "Coles Balaclava",
                "store_id": "571"
            },
            {
                "store_name": "Coles Ballarat (peel St)",
                "store_id": "628"
            },
            {
                "store_name": "Coles Ballarat (victoria St)",
                "store_id": "7798"
            },
            {
                "store_name": "Coles Bayswater",
                "store_id": "7804"
            },
            {
                "store_name": "Coles Belmont",
                "store_id": "501"
            },
            {
                "store_name": "Coles Belmont (high Street)",
                "store_id": "7796"
            },
            {
                "store_name": "Coles Benalla",
                "store_id": "7831"
            },
            {
                "store_name": "Coles Bendigo",
                "store_id": "638"
            },
            {
                "store_name": "Coles Bentleigh",
                "store_id": "595"
            },
            {
                "store_name": "Coles Berwick Central",
                "store_id": "7695"
            },
            {
                "store_name": "Coles Birallee Park",
                "store_id": "658"
            },
            {
                "store_name": "Coles Boronia",
                "store_id": "601"
            },
            {
                "store_name": "Coles Botanic Ridge",
                "store_id": "7733"
            },
            {
                "store_name": "Coles Brandon Park",
                "store_id": "540"
            },
            {
                "store_name": "Coles Brighton - Bay Street",
                "store_id": "7819"
            },
            {
                "store_name": "Coles Brimbank",
                "store_id": "7612"
            },
            {
                "store_name": "Coles Broadmeadows",
                "store_id": "569"
            },
            {
                "store_name": "Coles Bundoora",
                "store_id": "682"
            },
            {
                "store_name": "Coles Burnside",
                "store_id": "7793"
            },
            {
                "store_name": "Coles Burntbridge",
                "store_id": "7782"
            },
            {
                "store_name": "Coles Cairnlea",
                "store_id": "558"
            },
            {
                "store_name": "Coles Campbellfield",
                "store_id": "550"
            },
            {
                "store_name": "Coles Cardinia Lakes",
                "store_id": "7623"
            },
            {
                "store_name": "Coles Caroline Springs",
                "store_id": "554"
            },
            {
                "store_name": "Coles Carrum Downs",
                "store_id": "7935"
            },
            {
                "store_name": "Coles Casey Central",
                "store_id": "7697"
            },
            {
                "store_name": "Coles Caulfield Village",
                "store_id": "7724"
            },
            {
                "store_name": "Coles Chadstone",
                "store_id": "643"
            },
            {
                "store_name": "Coles Chadstone Village",
                "store_id": "7574"
            },
            {
                "store_name": "Coles Chirnside Park",
                "store_id": "622"
            },
            {
                "store_name": "Coles Clayton",
                "store_id": "581"
            },
            {
                "store_name": "Coles Clayton (centre Rd)",
                "store_id": "536"
            },
            {
                "store_name": "Coles Clyde North",
                "store_id": "7758"
            },
            {
                "store_name": "Coles Cobblebank",
                "store_id": "7761"
            },
            {
                "store_name": "Coles Cobram",
                "store_id": "7684"
            },
            {
                "store_name": "Coles Coburg North",
                "store_id": "7919"
            },
            {
                "store_name": "Coles Colac",
                "store_id": "7775"
            },
            {
                "store_name": "Coles Corio",
                "store_id": "511"
            },
            {
                "store_name": "Coles Cowes",
                "store_id": "7868"
            },
            {
                "store_name": "Coles Craigieburn",
                "store_id": "7611"
            },
            {
                "store_name": "Coles Craigieburn Village",
                "store_id": "7669"
            },
            {
                "store_name": "Coles Cranbourne",
                "store_id": "7918"
            },
            {
                "store_name": "Coles Cranbourne West",
                "store_id": "621"
            },
            {
                "store_name": "Coles Croydon",
                "store_id": "630"
            },
            {
                "store_name": "Coles Croydon North",
                "store_id": "510"
            },
            {
                "store_name": "Coles Cs Stctk Serv VIC  M2",
                "store_id": "5811"
            },
            {
                "store_name": "Coles Cs Stctk Serv VIC  M3",
                "store_id": "5812"
            },
            {
                "store_name": "Coles Cs Stctk Serv VIC M1",
                "store_id": "5810"
            },
            {
                "store_name": "Coles Dandenong",
                "store_id": "684"
            },
            {
                "store_name": "Coles Dandenong Plaza",
                "store_id": "660"
            },
            {
                "store_name": "Coles Daylesford",
                "store_id": "562"
            },
            {
                "store_name": "Coles Derrimut Village",
                "store_id": "613"
            },
            {
                "store_name": "Coles Diamond Creek",
                "store_id": "506"
            },
            {
                "store_name": "Coles Doncaster",
                "store_id": "7735"
            },
            {
                "store_name": "Coles Drouin",
                "store_id": "629"
            },
            {
                "store_name": "Coles Drysdale",
                "store_id": "7620"
            },
            {
                "store_name": "Coles Eastland",
                "store_id": "7881"
            },
            {
                "store_name": "Coles Echuca",
                "store_id": "620"
            },
            {
                "store_name": "Coles Eden Rise",
                "store_id": "544"
            },
            {
                "store_name": "Coles Elsternwick",
                "store_id": "7757"
            },
            {
                "store_name": "Coles Eltham",
                "store_id": "678"
            },
            {
                "store_name": "Coles Endeavour Hills",
                "store_id": "651"
            },
            {
                "store_name": "Coles Epping",
                "store_id": "654"
            },
            {
                "store_name": "Coles Ferntree Gully",
                "store_id": "528"
            },
            {
                "store_name": "Coles Fountain Gate",
                "store_id": "8786"
            },
            {
                "store_name": "Coles Frankston",
                "store_id": "652"
            },
            {
                "store_name": "Coles Geelong",
                "store_id": "7781"
            },
            {
                "store_name": "Coles Geelong West",
                "store_id": "7917"
            },
            {
                "store_name": "Coles Gisborne",
                "store_id": "606"
            },
            {
                "store_name": "Coles Glenroy",
                "store_id": "639"
            },
            {
                "store_name": "Coles Greensborough Plaza",
                "store_id": "657"
            },
            {
                "store_name": "Coles Greenvale",
                "store_id": "608"
            },
            {
                "store_name": "Coles Hallam",
                "store_id": "7716"
            },
            {
                "store_name": "Coles Hamilton",
                "store_id": "7600"
            },
            {
                "store_name": "Coles Hampton (bluff Road)",
                "store_id": "7787"
            },
            {
                "store_name": "Coles Harpley",
                "store_id": "7679"
            },
            {
                "store_name": "Coles Hastings",
                "store_id": "640"
            },
            {
                "store_name": "Coles Healesville",
                "store_id": "680"
            },
            {
                "store_name": "Coles Heritage Springs",
                "store_id": "603"
            },
            {
                "store_name": "Coles Hoppers Crossing",
                "store_id": "7718"
            },
            {
                "store_name": "Coles Horsham",
                "store_id": "615"
            },
            {
                "store_name": "Coles Kangaroo Flat",
                "store_id": "7618"
            },
            {
                "store_name": "Coles Karingal Hub",
                "store_id": "7690"
            },
            {
                "store_name": "Coles Keilor Downs",
                "store_id": "649"
            },
            {
                "store_name": "Coles Kilmore",
                "store_id": "552"
            },
            {
                "store_name": "Coles Knox",
                "store_id": "650"
            },
            {
                "store_name": "Coles Lalor",
                "store_id": "604"
            },
            {
                "store_name": "Coles Lalor Plaza",
                "store_id": "7786"
            },
            {
                "store_name": "Coles Langwarrin",
                "store_id": "670"
            },
            {
                "store_name": "Coles Lara",
                "store_id": "7776"
            },
            {
                "store_name": "Coles Leopold",
                "store_id": "538"
            },
            {
                "store_name": "Coles Lilydale Village",
                "store_id": "662"
            },
            {
                "store_name": "Coles Local Brighton",
                "store_id": "656"
            },
            {
                "store_name": "Coles Local St Kilda",
                "store_id": "668"
            },
            {
                "store_name": "Coles Local Toorak Village",
                "store_id": "7670"
            },
            {
                "store_name": "Coles Lynbrook",
                "store_id": "699"
            },
            {
                "store_name": "Coles Malvern",
                "store_id": "575"
            },
            {
                "store_name": "Coles Mambourin",
                "store_id": "4164"
            },
            {
                "store_name": "Coles Manor Lakes",
                "store_id": "556"
            },
            {
                "store_name": "Coles Maryborough",
                "store_id": "7992"
            },
            {
                "store_name": "Coles Mccrae",
                "store_id": "541"
            },
            {
                "store_name": "Coles Mcivor Rd",
                "store_id": "7838"
            },
            {
                "store_name": "Coles Melton South (station Square)",
                "store_id": "7619"
            },
            {
                "store_name": "Coles Mentone",
                "store_id": "546"
            },
            {
                "store_name": "Coles Mernda",
                "store_id": "7762"
            },
            {
                "store_name": "Coles Merrifield",
                "store_id": "7843"
            },
            {
                "store_name": "Coles Mildura (eighth St)",
                "store_id": "594"
            },
            {
                "store_name": "Coles Mildura (fifteenth St)",
                "store_id": "7840"
            },
            {
                "store_name": "Coles Mill Park Lakes",
                "store_id": "7705"
            },
            {
                "store_name": "Coles Moe",
                "store_id": "626"
            },
            {
                "store_name": "Coles Mooroolbark",
                "store_id": "570"
            },
            {
                "store_name": "Coles Mornington",
                "store_id": "673"
            },
            {
                "store_name": "Coles Mornington Tyabb Road",
                "store_id": "7266"
            },
            {
                "store_name": "Coles Morwell",
                "store_id": "561"
            },
            {
                "store_name": "Coles Myrtleford",
                "store_id": "7894"
            },
            {
                "store_name": "Coles Noble Park",
                "store_id": "549"
            },
            {
                "store_name": "Coles Northpoint",
                "store_id": "596"
            },
            {
                "store_name": "Coles Oakleigh",
                "store_id": "645"
            },
            {
                "store_name": "Coles Ocean Grove",
                "store_id": "665"
            },
            {
                "store_name": "Coles Online Hub Store Ocado - Melbourne - Team Shop",
                "store_id": "7593"
            },
            {
                "store_name": "Coles Online Hub Store Ocado Spoke - Dandenong",
                "store_id": "7655"
            },
            {
                "store_name": "Coles Pakenham",
                "store_id": "674"
            },
            {
                "store_name": "Coles Parkhill Junction",
                "store_id": "7731"
            },
            {
                "store_name": "Coles Parkmore",
                "store_id": "625"
            },
            {
                "store_name": "Coles Patterson Lakes",
                "store_id": "531"
            },
            {
                "store_name": "Coles Pinewood",
                "store_id": "504"
            },
            {
                "store_name": "Coles Plenty Valley",
                "store_id": "685"
            },
            {
                "store_name": "Coles Point Cook",
                "store_id": "537"
            },
            {
                "store_name": "Coles Prahran",
                "store_id": "573"
            },
            {
                "store_name": "Coles Reservoir",
                "store_id": "599"
            },
            {
                "store_name": "Coles Ringwood",
                "store_id": "637"
            },
            {
                "store_name": "Coles Riverside Plaza Kialla",
                "store_id": "7749"
            },
            {
                "store_name": "Coles Romsey",
                "store_id": "4045"
            },
            {
                "store_name": "Coles Rosebud",
                "store_id": "696"
            },
            {
                "store_name": "Coles Roxburgh Park",
                "store_id": "7703"
            },
            {
                "store_name": "Coles Sale",
                "store_id": "679"
            },
            {
                "store_name": "Coles Sanctuary Lakes",
                "store_id": "516"
            },
            {
                "store_name": "Coles Sandringham",
                "store_id": "641"
            },
            {
                "store_name": "Coles Sebastopol",
                "store_id": "7714"
            },
            {
                "store_name": "Coles Seymour",
                "store_id": "7780"
            },
            {
                "store_name": "Coles Shepparton",
                "store_id": "695"
            },
            {
                "store_name": "Coles Somerville",
                "store_id": "591"
            },
            {
                "store_name": "Coles Southland",
                "store_id": "669"
            },
            {
                "store_name": "Coles Springhill",
                "store_id": "7601"
            },
            {
                "store_name": "Coles Springvale",
                "store_id": "681"
            },
            {
                "store_name": "Coles St Germain",
                "store_id": "7748"
            },
            {
                "store_name": "Coles Stud Park",
                "store_id": "697"
            },
            {
                "store_name": "Coles Summerhill",
                "store_id": "7812"
            },
            {
                "store_name": "Coles Sunbury",
                "store_id": "648"
            },
            {
                "store_name": "Coles Swan Hill",
                "store_id": "574"
            },
            {
                "store_name": "Coles Tarneit Central",
                "store_id": "5802"
            },
            {
                "store_name": "Coles Tarneit Davis Road",
                "store_id": "5804"
            },
            {
                "store_name": "Coles Tarneit West",
                "store_id": "7717"
            },
            {
                "store_name": "Coles Taylors Hill",
                "store_id": "7841"
            },
            {
                "store_name": "Coles The Pines",
                "store_id": "524"
            },
            {
                "store_name": "Coles Tooronga",
                "store_id": "507"
            },
            {
                "store_name": "Coles Torquay",
                "store_id": "7693"
            },
            {
                "store_name": "Coles Traralgon",
                "store_id": "694"
            },
            {
                "store_name": "Coles Traralgon Village",
                "store_id": "4184"
            },
            {
                "store_name": "Coles Truganina",
                "store_id": "7685"
            },
            {
                "store_name": "Coles Tunstall Square",
                "store_id": "609"
            },
            {
                "store_name": "Coles Uni Hill",
                "store_id": "585"
            },
            {
                "store_name": "Coles Village Lakeside",
                "store_id": "520"
            },
            {
                "store_name": "Coles Wallan",
                "store_id": "7778"
            },
            {
                "store_name": "Coles Wangaratta",
                "store_id": "688"
            },
            {
                "store_name": "Coles Warragul",
                "store_id": "547"
            },
            {
                "store_name": "Coles Warrnambool",
                "store_id": "563"
            },
            {
                "store_name": "Coles Warrnambool (lava St)",
                "store_id": "7730"
            },
            {
                "store_name": "Coles Waurn Ponds",
                "store_id": "7810"
            },
            {
                "store_name": "Coles Wendouree",
                "store_id": "616"
            },
            {
                "store_name": "Coles Werribee",
                "store_id": "7777"
            },
            {
                "store_name": "Coles Werribee Plaza",
                "store_id": "691"
            },
            {
                "store_name": "Coles Wodonga",
                "store_id": "7698"
            },
            {
                "store_name": "Coles Wodonga Plaza",
                "store_id": "636"
            },
            {
                "store_name": "Coles Wonthaggi",
                "store_id": "8787"
            },
            {
                "store_name": "Coles Woodend",
                "store_id": "7616"
            },
            {
                "store_name": "Coles Woodgrove",
                "store_id": "519"
            },
            {
                "store_name": "Coles Woodlea",
                "store_id": "7844"
            },
            {
                "store_name": "Coles Wyndham Village",
                "store_id": "527"
            },
            {
                "store_name": "Unknown Supermarket Coles Ssc",
                "store_id": "7723"
            },
            {
                "store_name": "Coles Airport West",
                "store_id": "7808"
            },
            {
                "store_name": "Coles Armstrong Creek",
                "store_id": "7501"
            }
        ],
        "WA": [
            {
                "store_name": "Coles Alexander Heights",
                "store_id": "365"
            },
            {
                "store_name": "Coles Armadale",
                "store_id": "343"
            },
            {
                "store_name": "Coles Australind",
                "store_id": "327"
            },
            {
                "store_name": "Coles Balcatta",
                "store_id": "378"
            },
            {
                "store_name": "Coles Baldivis",
                "store_id": "287"
            },
            {
                "store_name": "Coles Banksia Grove",
                "store_id": "260"
            },
            {
                "store_name": "Coles Bassendean",
                "store_id": "395"
            },
            {
                "store_name": "Coles Beechboro",
                "store_id": "363"
            },
            {
                "store_name": "Coles Beeliar",
                "store_id": "494"
            },
            {
                "store_name": "Coles Beldon",
                "store_id": "336"
            },
            {
                "store_name": "Coles Belmont Forum",
                "store_id": "4824"
            },
            {
                "store_name": "Coles Brighton",
                "store_id": "290"
            },
            {
                "store_name": "Coles Bunbury Centrepoint",
                "store_id": "339"
            },
            {
                "store_name": "Coles Busselton",
                "store_id": "4836"
            },
            {
                "store_name": "Coles Busselton",
                "store_id": "291"
            },
            {
                "store_name": "Coles Byford",
                "store_id": "263"
            },
            {
                "store_name": "Coles Carousel",
                "store_id": "322"
            },
            {
                "store_name": "Coles Caversham",
                "store_id": "262"
            },
            {
                "store_name": "Coles Central Raine Square",
                "store_id": "481"
            },
            {
                "store_name": "Coles Chinatown",
                "store_id": "324"
            },
            {
                "store_name": "Coles Claremont",
                "store_id": "299"
            },
            {
                "store_name": "Coles Cockburn Gateway",
                "store_id": "490"
            },
            {
                "store_name": "Coles Collie",
                "store_id": "390"
            },
            {
                "store_name": "Coles Currambine",
                "store_id": "7542"
            },
            {
                "store_name": "Coles Dalyellup",
                "store_id": "7610"
            },
            {
                "store_name": "Coles Dianella",
                "store_id": "256"
            },
            {
                "store_name": "Coles Dunsborough",
                "store_id": "297"
            },
            {
                "store_name": "Coles Eaton Fair",
                "store_id": "493"
            },
            {
                "store_name": "Coles Ellenbrook",
                "store_id": "485"
            },
            {
                "store_name": "Coles Erskine",
                "store_id": "348"
            },
            {
                "store_name": "Coles Flinders Square",
                "store_id": "347"
            },
            {
                "store_name": "Coles Florida",
                "store_id": "7543"
            },
            {
                "store_name": "Coles Forest Lakes",
                "store_id": "306"
            },
            {
                "store_name": "Coles Forrestfield",
                "store_id": "353"
            },
            {
                "store_name": "Coles Fremantle",
                "store_id": "7544"
            },
            {
                "store_name": "Coles Galleria",
                "store_id": "334"
            },
            {
                "store_name": "Coles Garden City (booragoon)",
                "store_id": "332"
            },
            {
                "store_name": "Coles Geraldton",
                "store_id": "350"
            },
            {
                "store_name": "Coles Gosnells",
                "store_id": "384"
            },
            {
                "store_name": "Coles Greenwood",
                "store_id": "303"
            },
            {
                "store_name": "Coles Halls Head",
                "store_id": "257"
            },
            {
                "store_name": "Coles Haynes",
                "store_id": "282"
            },
            {
                "store_name": "Coles High Wycombe",
                "store_id": "285"
            },
            {
                "store_name": "Coles Hilton",
                "store_id": "7545"
            },
            {
                "store_name": "Coles Inglewood",
                "store_id": "383"
            },
            {
                "store_name": "Coles Innaloo Westfield",
                "store_id": "298"
            },
            {
                "store_name": "Coles Joondalup",
                "store_id": "335"
            },
            {
                "store_name": "Coles Kalamunda",
                "store_id": "394"
            },
            {
                "store_name": "Coles Kalgoorlie",
                "store_id": "4837"
            },
            {
                "store_name": "Coles Karawara",
                "store_id": "356"
            },
            {
                "store_name": "Coles Kardinya",
                "store_id": "391"
            },
            {
                "store_name": "Coles Karratha",
                "store_id": "313"
            },
            {
                "store_name": "Coles Karrinyup",
                "store_id": "205"
            },
            {
                "store_name": "Coles Kelmscott",
                "store_id": "345"
            },
            {
                "store_name": "Coles Kununurra",
                "store_id": "325"
            },
            {
                "store_name": "Coles Kwinana",
                "store_id": "488"
            },
            {
                "store_name": "Coles Lakelands",
                "store_id": "4796"
            },
            {
                "store_name": "Coles Local Angelo St",
                "store_id": "296"
            },
            {
                "store_name": "Coles Local Floreat",
                "store_id": "302"
            },
            {
                "store_name": "Coles Local Hillarys",
                "store_id": "371"
            },
            {
                "store_name": "Coles Local Mosman Park",
                "store_id": "392"
            },
            {
                "store_name": "Coles Local Shenton Park",
                "store_id": "7712"
            },
            {
                "store_name": "Coles Maddington",
                "store_id": "337"
            },
            {
                "store_name": "Coles Mandurah Forum",
                "store_id": "311"
            },
            {
                "store_name": "Coles Manjimup",
                "store_id": "388"
            },
            {
                "store_name": "Coles Margaret River",
                "store_id": "310"
            },
            {
                "store_name": "Coles Maylands",
                "store_id": "379"
            },
            {
                "store_name": "Coles Meadow Springs",
                "store_id": "362"
            },
            {
                "store_name": "Coles Melville",
                "store_id": "352"
            },
            {
                "store_name": "Coles Midland",
                "store_id": "278"
            },
            {
                "store_name": "Coles Mirrabooka",
                "store_id": "314"
            },
            {
                "store_name": "Coles Mundaring",
                "store_id": "330"
            },
            {
                "store_name": "Coles Narrogin",
                "store_id": "396"
            },
            {
                "store_name": "Coles Noranda Square",
                "store_id": "344"
            },
            {
                "store_name": "Coles North Armadale",
                "store_id": "381"
            },
            {
                "store_name": "Coles Northam",
                "store_id": "492"
            },
            {
                "store_name": "Coles Ocean Keys",
                "store_id": "375"
            },
            {
                "store_name": "Coles Pinjarra",
                "store_id": "293"
            },
            {
                "store_name": "Coles Riverton",
                "store_id": "465"
            },
            {
                "store_name": "Coles Rockingham Park",
                "store_id": "370"
            },
            {
                "store_name": "Coles Scarborough",
                "store_id": "380"
            },
            {
                "store_name": "Coles Secret Harbour",
                "store_id": "4790"
            },
            {
                "store_name": "Coles South Bunbury",
                "store_id": "399"
            },
            {
                "store_name": "Coles South Hedland",
                "store_id": "385"
            },
            {
                "store_name": "Coles South Lake",
                "store_id": "333"
            },
            {
                "store_name": "Coles Southern River",
                "store_id": "294"
            },
            {
                "store_name": "Coles Southern River East",
                "store_id": "4838"
            },
            {
                "store_name": "Coles Southlands",
                "store_id": "358"
            },
            {
                "store_name": "Coles Stocktake Service WA",
                "store_id": "5809"
            },
            {
                "store_name": "Coles Subiaco",
                "store_id": "270"
            },
            {
                "store_name": "Coles Swan View",
                "store_id": "398"
            },
            {
                "store_name": "Coles Tom Price",
                "store_id": "328"
            },
            {
                "store_name": "Coles Trinity Village",
                "store_id": "4815"
            },
            {
                "store_name": "Coles Vasse",
                "store_id": "268"
            },
            {
                "store_name": "Coles Victoria Park",
                "store_id": "340"
            },
            {
                "store_name": "Coles Wanneroo",
                "store_id": "289"
            },
            {
                "store_name": "Coles Warnbro",
                "store_id": "329"
            },
            {
                "store_name": "Coles Warwick Grove",
                "store_id": "338"
            },
            {
                "store_name": "Coles West Leederville",
                "store_id": "292"
            },
            {
                "store_name": "Coles Whiteman Edge",
                "store_id": "4839"
            },
            {
                "store_name": "Coles Whitford",
                "store_id": "489"
            },
            {
                "store_name": "Coles Yanchep",
                "store_id": "7680"
            },
            {
                "store_name": "Coles Albany",
                "store_id": "364"
            },
            {
                "store_name": "Coles Albany (orana)",
                "store_id": "478"
            }
        ]
    }
}